ListPage/__init__.py
ListPage/base_page.py
ListPage/common.py
ListPage/list_page.py
ListPage/memo.py
ListPage/paths.py
ListPage/scrolling_page.py
ListPage/targets.py
ListPage-1.0.5.dist-info/LICENSE
ListPage-1.0.5.dist-info/METADATA
ListPage-1.0.5.dist-info/WHEEL
ListPage-1.0.5.dist-info/top_level.txt
ListPage-1.0.5.dist-info/RECORD
