Metadata-Version: 2.1
Name: ListPage
Version: 1.0.5
Summary: Page classes dedicated to crawling or manipulating list web pages.
Home-page: https://gitee.com/Drission/ListPage
Author: g1879
Author-email: g1879@qq.com
License: BSD
Keywords: Page classes
Classifier: Programming Language :: Python :: 3.6
Classifier: Development Status :: 4 - Beta
Classifier: Topic :: Utilities
Classifier: License :: OSI Approved :: BSD License
Requires-Python: >=3.6
License-File: LICENSE
Requires-Dist: MixPage
Requires-Dist: DataRecorder
